biterator/__init__.py
biterator/_biterators.py
biterator/_bits.py
biterator/bits_exceptions.py
biterator/const.py
biterator-0.4.1.dist-info/WHEEL
biterator-0.4.1.dist-info/METADATA
biterator-0.4.1.dist-info/RECORD
