Metadata-Version: 2.1
Name: biterator
Version: 0.4.1
Summary: Bit manipulation and iteration tool suite.
License: MIT
Author: derek-strasters
Author-email: paracite.org@gmail.com
Requires-Python: ==3.8.10
Classifier: License :: OSI Approved :: MIT License
Classifier: Programming Language :: Python :: 3
